andi/Analysis_Instrument.py
andi/__init__.py
andi/dwfconstants.py
andi_py-1.1.0.dist-info/METADATA
andi_py-1.1.0.dist-info/WHEEL
andi_py-1.1.0.dist-info/top_level.txt
andi_py-1.1.0.dist-info/RECORD
