Metadata-Version: 2.1
Name: andi-py
Version: 1.1.0
Summary: Analog Discovery 2 python API
Home-page: https://github.com/fkolbl/andi
Author: Florian Kolbl - Yannick Bornat - Louis Regnacq
Project-URL: Documentation, https://andi.readthedocs.io
Project-URL: Source, https://github.com/fkolbl/andi
Keywords: osciloscope,hardware,electronics,measurements
Classifier: Development Status :: 5 - Production/Stable
Classifier: Programming Language :: Python :: 3.6
Classifier: Programming Language :: Python :: 3.7
Classifier: Programming Language :: Python :: 3.8
Classifier: Programming Language :: Python :: 3.9
Classifier: Programming Language :: Python :: 3.10
Classifier: Operating System :: Microsoft :: Windows
Classifier: Operating System :: POSIX :: Linux
Classifier: Operating System :: MacOS :: MacOS X
Classifier: Natural Language :: English
Requires-Python: >=3.6
Requires-Dist: numpy
